langserve_neuraflow/.DS_Store
langserve_neuraflow/__init__.py
langserve_neuraflow/api_handler.py
langserve_neuraflow/callbacks.py
langserve_neuraflow/chat_playground/dist/assets/index-a953ca96.css
langserve_neuraflow/chat_playground/dist/assets/index-fd666b8f.js
langserve_neuraflow/chat_playground/dist/favicon.ico
langserve_neuraflow/chat_playground/dist/index.html
langserve_neuraflow/client.py
langserve_neuraflow/lzstring.py
langserve_neuraflow/playground/dist/assets/index-52e8ab2f.css
langserve_neuraflow/playground/dist/assets/index-dbc96538.js
langserve_neuraflow/playground/dist/favicon.ico
langserve_neuraflow/playground/dist/index.html
langserve_neuraflow/playground.py
langserve_neuraflow/py.typed
langserve_neuraflow/pydantic_v1.py
langserve_neuraflow/schema.py
langserve_neuraflow/serialization.py
langserve_neuraflow/server.py
langserve_neuraflow/server_sent_events.py
langserve_neuraflow/validation.py
langserve_neuraflow/version.py
langserve_neuraflow-0.1.2.dist-info/LICENSE
langserve_neuraflow-0.1.2.dist-info/METADATA
langserve_neuraflow-0.1.2.dist-info/WHEEL
langserve_neuraflow-0.1.2.dist-info/RECORD
