Metadata-Version: 2.1
Name: langserve-neuraflow
Version: 0.1.2
Summary: Your description
Home-page: https://github.com/pascalnobereit/langserve
License: MIT
Author: Pascal Nobereit
Requires-Python: >=3.8.1,<4.0.0
Classifier: License :: OSI Approved :: MIT License
Classifier: Programming Language :: Python :: 3
Classifier: Programming Language :: Python :: 3.9
Classifier: Programming Language :: Python :: 3.10
Classifier: Programming Language :: Python :: 3.11
Classifier: Programming Language :: Python :: 3.12
Provides-Extra: all
Provides-Extra: client
Provides-Extra: server
Requires-Dist: fastapi (>=0.90.1,<1) ; extra == "server" or extra == "all"
Requires-Dist: httpx (>=0.23.0)
Requires-Dist: langchain-core (>=0.2.0,<0.3)
Requires-Dist: orjson (>=2)
Requires-Dist: pydantic (>=1)
Requires-Dist: sse-starlette (>=1.3.0,<2.0.0) ; extra == "server" or extra == "all"
Project-URL: Repository, https://github.com/pascalnobereit/langserve
